Opengis10ZhongwenWendang/README.md
Opengis10ZhongwenWendang/__init__.py
Opengis10ZhongwenWendang/__main__.py
Opengis10ZhongwenWendang/file.epub
Opengis10ZhongwenWendang/index.html
Opengis10ZhongwenWendang/css/__init__.py
Opengis10ZhongwenWendang/css/annotations.css
Opengis10ZhongwenWendang/css/main.css
Opengis10ZhongwenWendang/css/normalize.css
Opengis10ZhongwenWendang/css/popup.css
Opengis10ZhongwenWendang/font/__init__.py
Opengis10ZhongwenWendang/font/fontello.eot
Opengis10ZhongwenWendang/font/fontello.svg
Opengis10ZhongwenWendang/font/fontello.ttf
Opengis10ZhongwenWendang/font/fontello.woff
Opengis10ZhongwenWendang/img/__init__.py
Opengis10ZhongwenWendang/img/annotator-glyph-sprite.png
Opengis10ZhongwenWendang/img/annotator-icon-sprite.png
Opengis10ZhongwenWendang/img/apple-touch-icon.png
Opengis10ZhongwenWendang/img/cancelfullscreen.png
Opengis10ZhongwenWendang/img/close.png
Opengis10ZhongwenWendang/img/fullscreen.png
Opengis10ZhongwenWendang/img/loader.gif
Opengis10ZhongwenWendang/img/menu-icon.png
Opengis10ZhongwenWendang/img/save.png
Opengis10ZhongwenWendang/img/saved.png
Opengis10ZhongwenWendang/img/settings-s.png
Opengis10ZhongwenWendang/img/settings.png
Opengis10ZhongwenWendang/img/star.png
Opengis10ZhongwenWendang/js/__init__.py
Opengis10ZhongwenWendang/js/epub.js
Opengis10ZhongwenWendang/js/epub.min.js
Opengis10ZhongwenWendang/js/epub.min.map
Opengis10ZhongwenWendang/js/hooks.min.js
Opengis10ZhongwenWendang/js/hooks.min.map
Opengis10ZhongwenWendang/js/reader.js
Opengis10ZhongwenWendang/js/reader.js.map
Opengis10ZhongwenWendang/js/reader.min.js
Opengis10ZhongwenWendang/js/reader.min.map
Opengis10ZhongwenWendang/js/hooks/__init__.py
Opengis10ZhongwenWendang/js/hooks/extensions/__init__.py
Opengis10ZhongwenWendang/js/hooks/extensions/highlight.js
Opengis10ZhongwenWendang/js/libs/__init__.py
Opengis10ZhongwenWendang/js/libs/jquery.min.js
Opengis10ZhongwenWendang/js/libs/localforage.min.js
Opengis10ZhongwenWendang/js/libs/screenfull.js
opengis_1_0_zhongwen_wendang-2024.3.4.0.dist-info/METADATA
opengis_1_0_zhongwen_wendang-2024.3.4.0.dist-info/WHEEL
opengis_1_0_zhongwen_wendang-2024.3.4.0.dist-info/entry_points.txt
opengis_1_0_zhongwen_wendang-2024.3.4.0.dist-info/top_level.txt
opengis_1_0_zhongwen_wendang-2024.3.4.0.dist-info/RECORD
